{
	"name": "ADLSSalesOutput",
	"properties": {
		"linkedServiceName": {
			"referenceName": "ADLSSalesData",
			"type": "LinkedServiceReference",
			"parameters": {
				"StorageURL": "https://testingadls11.dfs.core.windows.net/",
				"ServicePrincipleID": "9fdbca0e-a279-4fb9-a3c4-0064279a69b9"
			}
		},
		"annotations": [],
		"type": "DelimitedText",
		"typeProperties": {
			"location": {
				"type": "AzureBlobFSLocation",
				"fileSystem": "testingdata"
			},
			"columnDelimiter": ",",
			"escapeChar": "\\",
			"firstRowAsHeader": true,
			"quoteChar": "\""
		},
		"schema": [
			{
				"name": "T2 PO Number",
				"type": "String"
			},
			{
				"name": "Shipment Number",
				"type": "String"
			},
			{
				"name": "Shipment Line",
				"type": "String"
			},
			{
				"name": "T2 Supplier Name",
				"type": "String"
			},
			{
				"name": "Part Number (MPN)",
				"type": "String"
			},
			{
				"name": "Ship To Location",
				"type": "String"
			},
			{
				"name": "Shipment Date",
				"type": "String"
			},
			{
				"name": "Masked Price",
				"type": "String"
			},
			{
				"name": "Negotiated Price",
				"type": "String"
			},
			{
				"name": "Pricing Delta",
				"type": "String"
			}
		]
	}
}